{
  "sections": {
    "collection-header": {
      "type": "collection-header",
      "disabled": true,
      "settings": {
        "enable": true,
        "collection_image_enable": true,
        "parallax": true,
        "parallax_direction": "top"
      }
    },
    "main-collection": {
      "type": "main-collection",
      "disabled": true,
      "settings": {
        "enable_sidebar": false,
        "collapsed": true,
        "filter_style": "sidebar",
        "enable_color_swatches": true,
        "enable_sort": true
      }
    },
    "text_and_image_NfUhcG": {
      "type": "text-and-image",
      "settings": {
        "image_width": 700,
        "subtitle": "",
        "title": "",
        "text": "",
        "button_label": "",
        "button_link": "",
        "button_style": "primary",
        "align_text": "left",
        "layout": "right",
        "divider": false
      }
    },
    "background_image_text_HwJp4B": {
      "type": "background-image-text",
      "settings": {
        "subtitle": "",
        "title": "",
        "text": "",
        "button_label": "",
        "button_link": "",
        "focal_point": "center",
        "layout": "left",
        "height": 550,
        "framed": false,
        "parallax": true,
        "parallax_direction": "top"
      }
    }
  },
  "order": [
    "collection-header",
    "main-collection",
    "text_and_image_NfUhcG",
    "background_image_text_HwJp4B"
  ]
}
